damakye_matrixsolver/__init__.py
damakye_matrixsolver/methods.py
damakye_matrixsolver/solver.py
damakye_matrixsolver/utils.py
tests/__init__.py
tests/test_solver.py
damakye_matrixsolver-0.1.dist-info/LICENCE.txt
damakye_matrixsolver-0.1.dist-info/METADATA
damakye_matrixsolver-0.1.dist-info/WHEEL
damakye_matrixsolver-0.1.dist-info/top_level.txt
damakye_matrixsolver-0.1.dist-info/RECORD
