Metadata-Version: 2.1
Name: damakye-matrixsolver
Version: 0.1
Summary: A Python package for solving systems of linear equations using various methods (e.g., Gaussian Elimination, LU Decomposition, Gauss-Jordan).
Home-page: https://github.com/DanielAgyekumamakyeGh/damakye_matrixsolver
Author: Daniel Agyekum Amakye
Author-email: your.janetobosuayaa@gmail.com.com
Classifier: Programming Language :: Python :: 3
Classifier: License :: OSI Approved :: MIT License
Classifier: Programming Language :: Python :: 3.7
Classifier: Programming Language :: Python :: 3.8
Classifier: Programming Language :: Python :: 3.9
Requires-Python: >=3.6
License-File: LICENCE.txt
Requires-Dist: numpy>=1.21.0
Requires-Dist: scipy>=1.7.0
